README.rst
setup.cfg
setup.py
src/buroca/__init__.py
src/buroca/__main__.py
src/buroca/cli.py
src/buroca/db.py
src/buroca/loffice.py
src/buroca/sheets.py
src/buroca/templates.py
src/buroca.egg-info/PKG-INFO
src/buroca.egg-info/SOURCES.txt
src/buroca.egg-info/dependency_links.txt
src/buroca.egg-info/entry_points.txt
src/buroca.egg-info/not-zip-safe
src/buroca.egg-info/requires.txt
src/buroca.egg-info/top_level.txt