Metadata-Version: 1.1
Name: buroca
Version: 0.1.10
Summary: A framework to help implementing Bureaucracy as code.
Home-page: https://github.com/fabiommendes/buroca
Author: Fábio Macêdo Mendes
Author-email: fabiomacedomendes@gmail.com
License: GNU General Public License (GPL)
Keywords: automation,devops,tools
Platform: UNKNOWN
Classifier: Development Status :: 4 - Beta
Classifier: Intended Audience :: Developers
Classifier: Operating System :: POSIX
Classifier: Programming Language :: Python
Classifier: Programming Language :: Python :: 3
Classifier: Programming Language :: Python :: 3.4
Classifier: Programming Language :: Python :: 3.5
Classifier: Programming Language :: Python :: 3.6
Classifier: Topic :: Software Development :: Libraries
